fastapi_prometheus_exporter/__init__.py
fastapi_prometheus_exporter/prometheus.py
fastapi_prometheus_exporter/py.typed
fastapi_prometheus_exporter-0.2.2.dist-info/LICENSE
fastapi_prometheus_exporter-0.2.2.dist-info/METADATA
fastapi_prometheus_exporter-0.2.2.dist-info/WHEEL
fastapi_prometheus_exporter-0.2.2.dist-info/RECORD
