Metadata-Version: 2.1
Name: fastapi-prometheus-exporter
Version: 0.2.2
Summary: FastAPI Prometheus Exporter
License: BSD-3-Clause
Author: Yibu Ma
Requires-Python: >=3.11,<4.0
Classifier: License :: OSI Approved :: BSD License
Classifier: Programming Language :: Python :: 3
Classifier: Programming Language :: Python :: 3.11
Classifier: Programming Language :: Python :: 3.12
Requires-Dist: fastapi (>=0.104.1,<0.105.0)
Requires-Dist: prometheus-client (>=0.19.0,<0.20.0)
